multi_agent_generator/__init__.py
multi_agent_generator/__main__.py
multi_agent_generator/generator.py
multi_agent_generator/model_inference.py
multi_agent_generator/evaluation/__init__.py
multi_agent_generator/evaluation/benchmark.py
multi_agent_generator/evaluation/evaluator.py
multi_agent_generator/evaluation/test_generator.py
multi_agent_generator/frameworks/__init__.py
multi_agent_generator/frameworks/agno_generator.py
multi_agent_generator/frameworks/crewai_flow_generator.py
multi_agent_generator/frameworks/crewai_generator.py
multi_agent_generator/frameworks/langgraph_generator.py
multi_agent_generator/frameworks/react_generator.py
multi_agent_generator/orchestration/__init__.py
multi_agent_generator/orchestration/orchestrator.py
multi_agent_generator/orchestration/patterns.py
multi_agent_generator/tools/__init__.py
multi_agent_generator/tools/tool_generator.py
multi_agent_generator/tools/tool_registry.py
multi_agent_generator-1.0.0.dist-info/licenses/LICENSE
multi_agent_generator-1.0.0.dist-info/METADATA
multi_agent_generator-1.0.0.dist-info/WHEEL
multi_agent_generator-1.0.0.dist-info/entry_points.txt
multi_agent_generator-1.0.0.dist-info/top_level.txt
multi_agent_generator-1.0.0.dist-info/RECORD
