Metadata-Version: 2.4
Name: multi-agent-generator
Version: 1.0.0
Summary: Generate multi-agent AI teams from plain English, supporting multiple LLM backends via LiteLLM
Home-page: https://github.com/aakriti1318/multi-agent-generator
Author: Aakriti Aggarwal
Author-email: aakritiaggarwal2k@gmail.com
License: MIT
Project-URL: Homepage, https://github.com/aakriti1318/multi-agent-generator
Project-URL: Bug Tracker, https://github.com/aakriti1318/multi-agent-generator/issues
Classifier: Development Status :: 5 - Production/Stable
Classifier: Intended Audience :: Developers
Classifier: License :: OSI Approved :: MIT License
Classifier: Programming Language :: Python :: 3
Classifier: Programming Language :: Python :: 3.8
Classifier: Programming Language :: Python :: 3.9
Classifier: Programming Language :: Python :: 3.10
Classifier: Programming Language :: Python :: 3.11
Classifier: Programming Language :: Python :: 3.12
Requires-Python: >=3.8
License-File: LICENSE
Requires-Dist: litellm>=0.1.0
Requires-Dist: streamlit>=1.22.0
Requires-Dist: langchain<0.4.0,>=0.3.0
Requires-Dist: langchain-core<0.4.0,>=0.3.0
Requires-Dist: langchain-openai<0.4.0,>=0.2.0
Requires-Dist: langgraph>=0.2.0
Requires-Dist: python-dotenv>=1.0.0
Requires-Dist: pydantic>=2.0.0
Requires-Dist: agno==1.8.4
Provides-Extra: watsonx
Requires-Dist: ibm-watsonx-ai>=0.2.0; extra == "watsonx"
Provides-Extra: dev
Requires-Dist: pytest>=7.0.0; extra == "dev"
Requires-Dist: black>=23.0.0; extra == "dev"
Requires-Dist: flake8>=6.0.0; extra == "dev"
Requires-Dist: twine; extra == "dev"
Requires-Dist: build; extra == "dev"
Dynamic: author
Dynamic: author-email
Dynamic: home-page
Dynamic: license-file
Dynamic: requires-python
